LICENSE
README.md
setup.cfg
setup.py
uaddress/__init__.py
uaddress/labels.py
uaddress/types.py
uaddress/uaddr.crfsuite
uaddress.egg-info/PKG-INFO
uaddress.egg-info/SOURCES.txt
uaddress.egg-info/dependency_links.txt
uaddress.egg-info/top_level.txt